justengel_material/__init__.py
justengel_material/__meta__.py
justengel_material/custom_template.py
justengel_material/utils.py
justengel_material/__pycache__/__init__.cpython-39.pyc
justengel_material/__pycache__/__meta__.cpython-39.pyc
justengel_material/__pycache__/custom_template.cpython-39.pyc
justengel_material/__pycache__/utils.cpython-39.pyc
justengel_material/static/justengel_material/default_background.png
justengel_material/static/justengel_material/default_background.svg
justengel_material/static/justengel_material/default_user.png
justengel_material/static/justengel_material/justengel_material.css
justengel_material/static/justengel_material/justengel_material.js
justengel_material/static/justengel_material/justengel_material_colors.js
justengel_material/templates/justengel_material/400.html
justengel_material/templates/justengel_material/403.html
justengel_material/templates/justengel_material/404.html
justengel_material/templates/justengel_material/500.html
justengel_material/templates/justengel_material/base.html
justengel_material/templates/justengel_material/begin_body.html
justengel_material/templates/justengel_material/container.html
justengel_material/templates/justengel_material/dynamic_css.html
justengel_material/templates/justengel_material/end_body.html
justengel_material/templates/justengel_material/extra_head.html
justengel_material/templates/justengel_material/footer.html
justengel_material/templates/justengel_material/head.html
justengel_material/templates/justengel_material/messages.html
justengel_material/templates/justengel_material/navbar.html
justengel_material/templates/justengel_material/navbar_items.html
justengel_material/templates/justengel_material/sidenav.html
justengel_material/templates/justengel_material/sidenav_items.html
justengel_material/templates/justengel_material/table_of_contents.html
justengel_material/templates/justengel_material/user/user_background.html
justengel_material-1.0.5.dist-info/LICENSE
justengel_material-1.0.5.dist-info/METADATA
justengel_material-1.0.5.dist-info/WHEEL
justengel_material-1.0.5.dist-info/top_level.txt
justengel_material-1.0.5.dist-info/RECORD
