Metadata-Version: 2.1
Name: justengel-material
Version: 1.0.5
Summary: Jinja Materializecss theme capability
Home-page: https://github.com/justengel-web/justengel_material
Author: Justin Engel
Author-email: jtengel08@gmail.com
License: Proprietary
Download-URL: https://github.com/justengel-web/justengel_material/archive/v1.0.5.tar.gz
Platform: any
Classifier: Programming Language :: Python
Classifier: Programming Language :: Python :: 3
Classifier: Operating System :: OS Independent
License-File: LICENSE
Requires-Dist: justengel-theme (>=0.0.2)
